<root><parking_spaces id="parking_usa"><space id="0"><top_left>38,368</top_left><bottom_right>69,390</bottom_right></space><space id="1"><top_left>48,347</top_left><bottom_right>79,357</bottom_right></space><space id="2"><top_left>59,328</top_left><bottom_right>84,336</bottom_right></space><space id="3"><top_left>69,312</top_left><bottom_right>88,318</bottom_right></space><space id="4"><top_left>72,301</top_left><bottom_right>94,303</bottom_right></space><space id="5"><top_left>80,293</top_left><bottom_right>96,296</bottom_right></space><space id="6"><top_left>85,282</top_left><bottom_right>101,287</bottom_right></space><space id="7"><top_left>100,342</top_left><bottom_right>134,351</bottom_right></space><space id="8"><top_left>100,321</top_left><bottom_right>139,329</bottom_right></space><space id="9"><top_left>101,362</top_left><bottom_right>139,377</bottom_right></space><space id="10"><top_left>242,278</top_left><bottom_right>264,284</bottom_right></space><space id="11"><top_left>252,285</top_left><bottom_right>278,291</bottom_right></space><space id="12"><top_left>263,296</top_left><bottom_right>286,301</bottom_right></space><space id="13"><top_left>268,305</top_left><bottom_right>296,316</bottom_right></space><space id="14"><top_left>283,319</top_left><bottom_right>318,333</bottom_right></space><space id="15"><top_left>297,338</top_left><bottom_right>345,359</bottom_right></space><space id="16"><top_left>328,292</top_left><bottom_right>354,299</bottom_right></space><space id="17"><top_left>344,311</top_left><bottom_right>393,322</bottom_right></space><space id="18"><top_left>358,324</top_left><bottom_right>402,340</bottom_right></space><space id="19"><top_left>366,249</top_left><bottom_right>371,255</bottom_right></space><space id="20"><top_left>380,252</top_left><bottom_right>387,261</bottom_right></space><space id="21"><top_left>400,253</top_left><bottom_right>405,267</bottom_right></space><space id="22"><top_left>411,262</top_left><bottom_right>421,276</bottom_right></space><space id="23"><top_left>427,266</top_left><bottom_right>440,283</bottom_right></space><space id="24"><top_left>447,274</top_left><bottom_right>460,289</bottom_right></space><space id="25"><top_left>473,279</top_left><bottom_right>491,298</bottom_right></space><space id="26"><top_left>499,287</top_left><bottom_right>521,305</bottom_right></space><space id="27"><top_left>529,292</top_left><bottom_right>552,314</bottom_right></space></parking_spaces></root>